spackage/init.py
spackage-0.1.dist-info/METADATA
spackage-0.1.dist-info/WHEEL
spackage-0.1.dist-info/top_level.txt
spackage-0.1.dist-info/RECORD
