Metadata-Version: 2.1
Name: spackage
Version: 0.1
Summary: This is a Description
Author: Sir Qasim and Shahzad Khan
License: UNKNOWN
Platform: UNKNOWN
